toflat/__init__.py
toflat/toflat.py
toflat/data/jgd2011_plane_rect_crs.geojson
toflat-0.1.dist-info/LICENSE
toflat-0.1.dist-info/METADATA
toflat-0.1.dist-info/WHEEL
toflat-0.1.dist-info/top_level.txt
toflat-0.1.dist-info/RECORD
