Metadata-Version: 2.1
Name: toflat
Version: 0.1
Summary: toflat: Japanese latlong to xy.
Author-email: HideyukiO <hogawa098@gmail.com>
License: MIT License
Project-URL: Repository, https://github.com/mazarimono/toflat
Keywords: plane_rectangle,GIS
Classifier: Programming Language :: Python :: 3
Classifier: Programming Language :: Python :: 3.10
Classifier: Programming Language :: Python :: 3.11
Requires-Python: >=3.10
License-File: LICENSE
Requires-Dist: geopandas
Provides-Extra: dev
Requires-Dist: black ; extra == 'dev'
Requires-Dist: isort ; extra == 'dev'
Requires-Dist: flake8 ; extra == 'dev'
Requires-Dist: mypy ; extra == 'dev'
Requires-Dist: pytest ; extra == 'dev'
